pypgoptimizator
