Metadata-Version: 1.0
Name: pypgoptimizator
Version: 1.4
Summary: Postgresql configuration optimizator
Home-page: http://git.minitage.org/git/others/pypgoptimizator/
Author: UNKNOWN
Author-email: UNKNOWN
License: BSD
Platform: UNKNOWN
